{
    "cluster_name": "my_cluster",
    "spark_version": "15.4.x-scala2.12",
    "azure_attributes": {
        "first_on_demand": 1,
        "spot_bid_max_price": -1
    },
    "node_type_id": "Standard_D4s_v3",
    "autotermination_minutes": 45,
    "enable_elastic_disk": true,
    "enable_local_disk_encryption": false,
    "data_security_mode": "DATA_SECURITY_MODE_STANDARD",
    "runtime_engine": "STANDARD",
    "kind": "CLASSIC_PREVIEW",
    "use_ml_runtime": false,
    "is_single_node": true,
    "num_workers": 0,
    "apply_policy_default_values": false
}